{
	"movieInfoResult": {
		"movieInfo": {
			"movieCd": "20176781",
			"movieNm": "내가 죽기 전에 가장 듣고 싶은 말",
			"movieNmEn": "The Last Word",
			"movieNmOg": "",
			"showTm": "107",
			"prdtYear": "2017",
			"openDt": "20170719",
			"prdtStatNm": "개봉",
			"typeNm": "장편",
			"nations": [
				{
					"nationNm": "미국"
				}
			],
			"genres": [
				{
					"genreNm": "코미디"
				}
			],
			"directors": [
				{
					"peopleNm": "마크 펠링톤",
					"peopleNmEn": "Mark Pellington"
				}
			],
			"actors": [
				{
					"peopleNm": "셜리 맥클레인",
					"peopleNmEn": "Shirley Maclaine",
					"cast": "",
					"castEn": ""
				},
				{
					"peopleNm": "아만다 사이프리드",
					"peopleNmEn": "Amanda Seyfried",
					"cast": "",
					"castEn": ""
				},
				{
					"peopleNm": "앤 헤이시",
					"peopleNmEn": "Anne Heche",
					"cast": "",
					"castEn": ""
				}
			],
			"showTypes": [
				{
					"showTypeGroupNm": "2D",
					"showTypeNm": "디지털"
				}
			],
			"companys": [
				{
					"companyCd": "20111583",
					"companyNm": "(주)메인타이틀픽쳐스",
					"companyNmEn": "",
					"companyPartNm": "배급사"
				},
				{
					"companyCd": "20161681",
					"companyNm": "주식회사 키위컴퍼니",
					"companyNmEn": "Kiwi Company Co., Ltd",
					"companyPartNm": "배급사"
				},
				{
					"companyCd": "20111583",
					"companyNm": "(주)메인타이틀픽쳐스",
					"companyNmEn": "",
					"companyPartNm": "수입사"
				}
			],
			"audits": [
				{
					"auditNo": "2017-MF00775",
					"watchGradeNm": "12세이상관람가"
				}
			],
			"staffs": []
		},
		"source": "영화진흥위원회"
	}
}