{
	"movieInfoResult": {
		"movieInfo": {
			"movieCd": "20176201",
			"movieNm": "더 서클",
			"movieNmEn": "The Circle",
			"movieNmOg": "",
			"showTm": "109",
			"prdtYear": "2017",
			"openDt": "20170622",
			"prdtStatNm": "개봉",
			"typeNm": "장편",
			"nations": [
				{
					"nationNm": "미국"
				}
			],
			"genres": [
				{
					"genreNm": "드라마"
				},
				{
					"genreNm": "SF"
				},
				{
					"genreNm": "스릴러"
				}
			],
			"directors": [
				{
					"peopleNm": "제임스 폰솔트",
					"peopleNmEn": "James Ponsoldt"
				}
			],
			"actors": [
				{
					"peopleNm": "엠마 왓슨",
					"peopleNmEn": "Emma Watson",
					"cast": "",
					"castEn": ""
				},
				{
					"peopleNm": "톰 행크스",
					"peopleNmEn": "Tom Hanks",
					"cast": "",
					"castEn": ""
				}
			],
			"showTypes": [
				{
					"showTypeGroupNm": "2D",
					"showTypeNm": "디지털"
				}
			],
			"companys": [
				{
					"companyCd": "20168728",
					"companyNm": "씨네그루(주)키다리이엔티",
					"companyNmEn": "KIDARI ENT",
					"companyPartNm": "배급사"
				},
				{
					"companyCd": "20111583",
					"companyNm": "(주)메인타이틀픽쳐스",
					"companyNmEn": "",
					"companyPartNm": "수입사"
				}
			],
			"audits": [
				{
					"auditNo": "2017-MF00821",
					"watchGradeNm": "12세이상관람가"
				}
			],
			"staffs": []
		},
		"source": "영화진흥위원회"
	}
}