{
	"movieInfoResult": {
		"movieInfo": {
			"movieCd": "20179186",
			"movieNm": "이모티: 더 무비",
			"movieNmEn": "The Emoji Movie",
			"movieNmOg": "",
			"showTm": "91",
			"prdtYear": "2017",
			"openDt": "20170802",
			"prdtStatNm": "개봉",
			"typeNm": "장편",
			"nations": [
				{
					"nationNm": "미국"
				}
			],
			"genres": [
				{
					"genreNm": "애니메이션"
				},
				{
					"genreNm": "어드벤처"
				}
			],
			"directors": [
				{
					"peopleNm": "토니 레온디스",
					"peopleNmEn": "Tony Leondis"
				}
			],
			"actors": [
				{
					"peopleNm": "T.J. 밀러",
					"peopleNmEn": "T.J. Miller",
					"cast": "진 목소리",
					"castEn": ""
				},
				{
					"peopleNm": "제임스 코든",
					"peopleNmEn": "James Corden",
					"cast": "하이파이브 목소리",
					"castEn": ""
				},
				{
					"peopleNm": "안나 패리스",
					"peopleNmEn": "Anna Faris",
					"cast": "핵키 브레이크 목소리",
					"castEn": ""
				},
				{
					"peopleNm": "패트릭 스튜어트",
					"peopleNmEn": "Patrick Stewart",
					"cast": "떵 목소리",
					"castEn": ""
				}
			],
			"showTypes": [
				{
					"showTypeGroupNm": "2D",
					"showTypeNm": "디지털"
				},
				{
					"showTypeGroupNm": "2D",
					"showTypeNm": "디지털더빙"
				}
			],
			"companys": [
				{
					"companyCd": "20173221",
					"companyNm": "소니픽쳐스엔터테인먼트코리아주식회사극장배급지점",
					"companyNmEn": "Sony Pictures Releasing International",
					"companyPartNm": "배급사"
				},
				{
					"companyCd": "20173221",
					"companyNm": "소니픽쳐스엔터테인먼트코리아주식회사극장배급지점",
					"companyNmEn": "Sony Pictures Releasing International",
					"companyPartNm": "수입사"
				}
			],
			"audits": [
				{
					"auditNo": "2017-MF01244",
					"watchGradeNm": "전체관람가"
				}
			],
			"staffs": []
		},
		"source": "영화진흥위원회"
	}
}